frasco_statsd.py
setup.py
frasco_statsd.egg-info/PKG-INFO
frasco_statsd.egg-info/SOURCES.txt
frasco_statsd.egg-info/dependency_links.txt
frasco_statsd.egg-info/not-zip-safe
frasco_statsd.egg-info/requires.txt
frasco_statsd.egg-info/top_level.txt