Metadata-Version: 1.0
Name: frasco-statsd
Version: 0.1
Summary: Statsd integration for Frasco
Home-page: http://github.com/frascoweb/frasco-statsd
Author: Maxime Bouroumeau-Fuseau
Author-email: maxime.bouroumeau@gmail.com
License: MIT
Platform: any
